Workbook

Sheet MF_4
A1: DATE | C1: Axis Small Cap Fund | E1: Axis Bluechip Fund | G1: SBI Small Cap Fund | I1: SBI Bluechip Fund | K1: ICICI prudential small cap fund | M1: ICICI prudential bluechip fund | O1: Mirae Asset Large Cap Fund | Q1: Nippon India Small Cap Fund | S1: Nippon India Large Cap Fund | U1: Franklin India Smaller Companies Fund | W1: Quant Small Cap Fund | Y1: Bank of India Small Cap Fund | AA1: Bank of India Bluechip Fund | AC1: Edelweiss Small Cap Fund | AE1: Edelweiss Large Cap Fund | AG1: UTI Small Cap Fund | AI1: Tata Small Cap Fund | AK1: Bandhan Small Cap Fund | AM1: Bandhan Large Cap Fund | AO1: Hdfc Small Cap Fund
A2: TYPE | C2: Small Cap | E2: Large Cap | G2: Small Cap | I2: Large Cap | K2: Small Cap | M2: Large Cap | O2: Large Cap | Q2: Small Cap | S2: Large Cap | U2: Small Cap | W2: Small Cap | Y2: Small Cap | AA2: Large Cap | AC2: Small Cap | AE2: Large Cap | AG2: Small Cap | AI2: Small Cap | AK2: Small Cap | AM2: Large Cap | AO2: Small Cap
A3: Scheme | C3: Regular | E3: Regular | G3: Regular | I3: Regular | K3: Regular | M3: Regular | O3: Regular | Q3: Regular | S3: Regular | U3: Regular | W3: Regular | Y3: Regular | AA3: Regular | AC3: Regular | AE3: Regular | AG3: Regular | AI3: Regular | AK3: Regular | AM3: Regular | AO3: Regular
A5: 45383 | C5: 87.6 | E5: 54.97 | G5: 151.447 | I5: 80.5753 | K5: 76.22 | M5: 96.69 | O5: 97.174 | Q5: 144.2327 | S5: 79.0111 | U5: 150.0304 | W5: 236.082
A6: 45384 | C6: 88.31 | E6: 54.91 | G6: 152.3349 | I6: 80.5901 | K6: 76.83 | M6: 96.48 | O6: 97.052 | Q6: 145.2666 | S6: 79.0297 | U6: 151.4008 | W6: 238.6036
A7: 45385 | C7: 88.81 | E7: 54.83 | G7: 153.5379 | I7: 80.4234 | K7: 77.51 | M7: 96.37 | O7: 97.164 | Q7: 146.16 | S7: 79.2019 | U7: 152.7398 | W7: 240.7754
A8: 45386 | C8: 89.22 | E8: 55.15 | G8: 154.3682 | I8: 80.6113 | K8: 77.76 | M8: 96.37 | O8: 97.39 | Q8: 146.6017 | S8: 79.4045 | U8: 153.533 | W8: 241.6104
A9: 45387 | C9: 89.27 | E9: 55.11 | G9: 154.9984 | I9: 80.6936 | K9: 78.05 | M9: 96.22 | O9: 97.589 | Q9: 147.0745 | S9: 79.6573 | U9: 153.9159 | W9: 243.8755
A10: 45388
A11: 45389
A12: 45390 | C12: 89.26 | E12: 55.51 | G12: 155.1729 | I12: 81.2149 | K12: 78.01 | M12: 97.09 | O12: 98.303 | Q12: 147.414 | S12: 80.1553 | U12: 154.313 | W12: 244.2302
A13: 45391 | C13: 89.05 | E13: 55.51 | G13: 154.9404 | I13: 81.2663 | K13: 77.79 | M13: 96.99 | O13: 98.269 | Q13: 147.0104 | S13: 80.0982 | U13: 154.3693 | W13: 245.2582
A14: 45392 | C14: 89.7 | E14: 55.74 | G14: 156.363 | I14: 81.5339 | K14: 78.21 | M14: 97.47 | O14: 98.81 | Q14: 147.9301 | S14: 80.3572 | U14: 155.3222 | W14: 246.7727
A15: 45393
A16: 45394 | C16: 89.15 | E16: 55.31 | G16: 155.3692 | I16: 80.8902 | K16: 77.79 | M16: 96.45 | O16: 97.972 | Q16: 147.2647 | S16: 79.6519 | U16: 155.1037 | W16: 245.5723
A17: 45395
A18: 45396
A19: 45397 | C19: 88.12 | E19: 54.52 | G19: 153.8999 | I19: 79.961 | K19: 76.92 | M19: 95.54 | O19: 96.716 | Q19: 145.4838 | S19: 78.6132 | U19: 153.7621 | W19: 242.1028
A20: 45398 | C20: 88.29 | E20: 54.14 | G20: 154.3259 | I20: 79.6976 | K20: 77.08 | M20: 95.12 | O20: 96.292 | Q20: 146.0726 | S20: 78.3847 | U20: 154.6943 | W20: 242.7028
A21: 45399
A22: 45400 | C22: 88.13 | E22: 53.84 | G22: 154.4104 | I22: 79.4172 | K22: 77.11 | M22: 94.68 | O22: 95.905 | Q22: 146.2187 | S22: 77.9006 | U22: 154.9481 | W22: 243.4643
A23: 45401 | C23: 88.01 | E23: 54.15 | G23: 155.1999 | I23: 79.7929 | K23: 77.08 | M23: 94.87 | O23: 96.492 | Q23: 146.4296 | S23: 78.4604 | U23: 154.3694 | W23: 243.591
A24: 45402
A25: 45403
A26: 45404 | C26: 88.46 | E26: 54.74 | G26: 156.6142 | I26: 80.3626 | K26: 77.55 | M26: 95.89 | O26: 97.405 | Q26: 148.6977 | S26: 79.2171 | U26: 155.5495 | W26: 246.0378
A27: 45405 | C27: 89.4 | E27: 54.79 | G27: 157.4494 | I27: 80.5905 | K27: 77.96 | M27: 96.09 | O27: 97.787 | Q27: 149.9781 | S27: 79.3513 | U27: 156.7698 | W27: 247.6619
A28: 45406 | C28: 90.1 | E28: 54.9 | G28: 158.6155 | I28: 80.8967 | K28: 78.47 | M28: 96.37 | O28: 98.036 | Q28: 150.8558 | S28: 79.4991 | U28: 157.7147 | W28: 248.8812
A29: 45407 | C29: 90.73 | E29: 54.98 | G29: 159.4081 | I29: 80.8755 | K29: 78.74 | M29: 97.14 | O29: 98.536 | Q29: 152.2396 | S29: 80.2961 | U29: 159.2307 | W29: 250.0449
A30: 45408 | C30: 90.77 | E30: 54.45 | G30: 159.3956 | I30: 80.4151 | K30: 78.87 | M30: 96.98 | O30: 98.08 | Q30: 153.0103 | S30: 79.8894 | U30: 160.0277 | W30: 251.2537
A31: 45409
A32: 45410
A33: 45411 | C33: 90.56 | E33: 54.92 | G33: 159.9382 | I33: 81.0525 | K33: 78.98 | M33: 97.82 | O33: 98.907 | Q33: 153.6303 | S33: 80.7148 | U33: 160.5925 | W33: 252.3833
A34: 45412 | C34: 90.95 | E34: 55.03 | G34: 160.2713 | I34: 81.1084 | K34: 79.44 | M34: 97.79 | O34: 98.716 | Q34: 154.3008 | S34: 80.7215 | U34: 161.1059 | W34: 252.468
A35: 45413
A36: 45414 | C36: 90.92 | E36: 55.25 | G36: 160.6105 | I36: 81.2264 | K36: 79.63 | M36: 98.01 | O36: 98.723 | Q36: 154.9645 | S36: 80.9278 | U36: 161.5322 | W36: 252.6756
A37: 45415 | C37: 90.39 | E37: 54.9 | G37: 159.5067 | I37: 80.8942 | K37: 79.42 | M37: 97.24 | O37: 97.991 | Q37: 154.0879 | S37: 80.3953 | U37: 160.7014 | W37: 250.8884
A38: 45416
A39: 45417
A40: 45418 | C40: 90.18 | E40: 54.83 | G40: 158.8203 | I40: 81.2529 | K40: 79.22 | M40: 96.98 | O40: 97.888 | Q40: 152.6317 | S40: 80.0205 | U40: 160.4843 | W40: 246.9053
A41: 45419 | C41: 89.15 | E41: 54.44 | G41: 157.4357 | I41: 80.8533 | K41: 78.59 | M41: 96.11 | O41: 97.35 | Q41: 150.7162 | S41: 79.4972 | U41: 158.3828 | W41: 242.9962
A42: 45420 | C42: 89.37 | E42: 54.59 | G42: 158.1631 | I42: 80.8986 | K42: 79.07 | M42: 96.58 | O42: 97.341 | Q42: 151.6701 | S42: 79.6293 | U42: 159.3186 | W42: 244.7069
A43: 45421 | C43: 88.04 | E43: 53.95 | G43: 154.5325 | I43: 79.7166 | K43: 77.82 | M43: 95.17 | O43: 96.027 | Q43: 148.3951 | S43: 78.2239 | U43: 156.131 | W43: 239.1849
A44: 45422 | C44: 88.43 | E44: 54.28 | G44: 155.2362 | I44: 80.1493 | K44: 78 | M44: 95.85 | O44: 96.528 | Q44: 149.4332 | S44: 78.7968 | U44: 156.631 | W44: 240.9784
A45: 45423
A46: 45424
A47: 45425 | C47: 88.3 | E47: 54.3 | G47: 155.2467 | I47: 80.5402 | K47: 78.06 | M47: 96.09 | O47: 96.67 | Q47: 149.5538 | S47: 78.9586 | U47: 155.8152 | W47: 240.4643
A48: 45426 | C48: 89.25 | E48: 54.43 | G48: 156.9741 | I48: 80.9132 | K48: 78.78 | M48: 96.64 | O48: 97.194 | Q48: 151.8998 | S48: 79.3673 | U48: 158.1376 | W48: 245.1278
A49: 45427 | C49: 90.18 | E49: 54.49 | G49: 158.5376 | I49: 80.9221 | K49: 79.51 | M49: 96.88 | O49: 97.294 | Q49: 153.9042 | S49: 79.556 | U49: 160.0519 | W49: 246.2023
A50: 45428 | C50: 91.27 | E50: 55.01 | G50: 160.6291 | I50: 81.6685 | K50: 80.53 | M50: 97.65 | O50: 98.16 | Q50: 156.0388 | S50: 80.3584 | U50: 161.82 | W50: 247.2793
A51: 45429 | C51: 92.64 | E51: 55.24 | G51: 162.1753 | I51: 82.0646 | K51: 81.61 | M51: 98 | O51: 98.661 | Q51: 157.8758 | S51: 80.7185 | U51: 164.3933 | W51: 249.7467
A52: 45430
A53: 45431
A54: 45432
A55: 45433 | C55: 92.84 | E55: 55.33 | G55: 163.1345 | I55: 82.125 | K55: 81.85 | M55: 98.15 | O55: 98.899 | Q55: 158.1515 | S55: 81.0568 | U55: 164.2216 | W55: 252.5836
A56: 45434 | C56: 92.84 | E56: 55.49 | G56: 163.4808 | I56: 82.4894 | K56: 82.27 | M56: 98.4 | O56: 99.226 | Q56: 158.4567 | S56: 81.3784 | U56: 164.3703 | W56: 254.1452
A57: 45435 | C57: 93.1 | E57: 56.18 | G57: 163.2055 | I57: 83.4662 | K57: 82.7 | M57: 99.71 | O57: 100.517 | Q57: 158.8619 | S57: 82.3664 | U57: 164.7321 | W57: 254.7841
A58: 45436 | C58: 93.01 | E58: 56.01 | G58: 162.6407 | I58: 83.3747 | K58: 82.59 | M58: 99.74 | O58: 100.543 | Q58: 159.0514 | S58: 82.3253 | U58: 164.9255 | W58: 254.4
A59: 45437
A60: 45438
A61: 45439 | C61: 93.08 | E61: 55.87 | G61: 162.3966 | I61: 83.5136 | K61: 82.36 | M61: 99.53 | O61: 0.527 | Q61: 158.6232 | S61: 82.2051 | U61: 165.2473 | W61: 254.3219
A62: 45440 | C62: 92.28 | E62: 55.6 | G62: 161.8002 | I62: 83.3905 | K62: 81.88 | M62: 99.3 | O62: 100.247 | Q62: 157.2219 | S62: 81.8703 | U62: 163.862 | W62: 252.2657
A63: 45441 | C63: 92.35 | E63: 55.16 | G63: 162.3466 | I63: 82.8836 | K63: 82.03 | M63: 98.45 | O63: 99.472 | Q63: 157.0454 | S63: 81.1713 | U63: 163.8899 | W63: 252.2353
A64: 45442 | C64: 91.41 | E64: 54.63 | G64: 160.6395 | I64: 82.422 | K64: 80.84 | M64: 97.69 | O64: 98.801 | Q64: 155.6176 | S64: 80.5746 | U64: 162.7249 | W64: 248.0526
A65: 45443 | C65: 92.21 | E65: 54.67 | G65: 162.0162 | I65: 82.3445 | K65: 80.85 | M65: 97.8 | O65: 98.961 | Q65: 156.2529 | S65: 80.9845 | U65: 164.165 | W65: 251.246
A66: 45444
A67: 45445
A68: 45446 | C68: 93.78 | E68: 56.24 | G68: 164.9698 | I68: 84.4289 | K68: 82.44 | M68: 100.81 | O68: 101.751 | Q68: 159.591 | S68: 83.6755 | U68: 167.5042 | W68: 257.7739
A69: 45447 | C69: 89.24 | E69: 53.54 | G69: 157.4136 | I69: 80.6477 | K69: 78.01 | M69: 94.96 | O69: 96.09 | Q69: 148.5354 | S69: 78.1305 | U69: 157.4201 | W69: 236.4661
A70: 45448 | C70: 91.16 | E70: 55.4 | G70: 161.5492 | I70: 83.1941 | K70: 80.07 | M70: 97.9 | O70: 99.398 | Q70: 152.9679 | S70: 80.6756 | U70: 162.273 | W70: 245.2512
A71: 45449 | C71: 93.41 | E71: 55.76 | G71: 164.5974 | I71: 83.9987 | K71: 82.17 | M71: 98.72 | O71: 100.576 | Q71: 157.1096 | S71: 81.5876 | U71: 166.6355 | W71: 252.9919
A72: 45450 | C72: 95.15 | E72: 56.85 | G72: 167.295 | I72: 85.1902 | K72: 83.75 | M72: 100.53 | O72: 102.379 | Q72: 160.432 | S72: 83.1511 | U72: 169.8459 | W72: 257.8042
A73: 45451
A74: 45452
A75: 45453 | C75: 96.04 | E75: 56.91 | G75: 169.7371 | I75: 85.1962 | K75: 84.58 | M75: 100.81 | O75: 102.462 | Q75: 162.0128 | S75: 83.2841 | U75: 172.0605 | W75: 257.1288
A76: 45454 | C76: 96.52 | E76: 56.84 | G76: 170.954 | I76: 85.1522 | K76: 85 | M76: 100.94 | O76: 102.469 | Q76: 163.5781 | S76: 83.3825 | U76: 172.5483 | W76: 259.0481
A77: 45455 | C77: 97.07 | E77: 56.93 | G77: 172.4547 | I77: 85.5156 | K77: 85.73 | M77: 101.29 | O77: 102.854 | Q77: 165.2095 | S77: 83.7793 | U77: 173.7931 | W77: 261.6361
A78: 45456 | C78: 97.78 | E78: 57.27 | G78: 173.3299 | I78: 86.089 | K78: 86.26 | M78: 101.61 | O78: 103.18 | Q78: 166.5515 | S78: 84.2107 | U78: 175.5986 | W78: 263.2726
A79: 45457 | C79: 98.89 | E79: 57.58 | G79: 174.8164 | I79: 86.6995 | K79: 86.72 | M79: 101.97 | O79: 103.625 | Q79: 167.9978 | S79: 84.7667 | U79: 176.9002 | W79: 264.9236
A80: 45458
A81: 45459
A82: 45460
A83: 45461 | C83: 99.47 | E83: 57.99 | G83: 174.9076 | I83: 86.908 | K83: 86.91 | M83: 102.14 | O83: 104.2 | Q83: 169.6365 | S83: 84.891 | U83: 177.7779 | W83: 266.6945
A84: 45462 | C84: 98.82 | E84: 57.71 | G84: 174.5616 | I84: 86.5808 | K84: 86.23 | M84: 101.53 | O84: 104.159 | Q84: 168.5444 | S84: 84.6916 | U84: 177.1023 | W84: 266.3561
A85: 45463 | C85: 99.02 | E85: 57.63 | G85: 175.3225 | I85: 86.7801 | K85: 86.72 | M85: 101.7 | O85: 104.536 | Q85: 169.0149 | S85: 84.9524 | U85: 178.1564 | W85: 268.3626
A86: 45464 | C86: 98.68 | E86: 57.43 | G86: 175.4179 | I86: 86.4432 | K86: 86.5 | M86: 101.4 | O86: 104.387 | Q86: 168.6822 | S86: 84.6593 | U86: 178.2937 | W86: 267.3457
A87: 45465 | W87: 265.5694
A88: 45466
A89: 45467 | C89: 98.88 | E89: 57.71 | G89: 175.5097 | I89: 86.8097 | K89: 86.86 | M89: 101.64 | O89: 104.545 | Q89: 169.4259 | S89: 84.8211 | U89: 178.6959
A90: 45468 | C90: 99.45 | E90: 57.97 | G90: 175.7913 | I90: 87.1903 | K90: 87.06 | M90: 102.2 | O90: 105.379 | Q90: 169.2716 | S90: 85.4002 | U90: 179.0852 | W90: 265.4977
A91: 45469 | C91: 99.25 | E91: 58.28 | G91: 175.2521 | I91: 87.4919 | K91: 87.29 | M91: 102.87 | O91: 105.933 | Q91: 169.6483 | S91: 85.6349 | U91: 179.7453 | W91: 266.8686
A92: 45470 | C92: 98.95 | E92: 58.66 | G92: 174.2407 | I92: 88.0615 | K92: 87.17 | M92: 103.64 | O92: 106.484 | Q92: 168.9286 | S92: 86.0678 | U92: 178.458 | W92: 265.7298
A93: 45471 | C93: 99.68 | E93: 58.38 | G93: 174.5305 | I93: 87.7136 | K93: 87.52 | M93: 103.49 | O93: 106.131 | Q93: 169.7002 | S93: 85.901 | U93: 179.9416 | W93: 266.4957
A94: 45472
A95: 45473 | G95: 174.5224 | I95: 87.7071
A96: 45474 | C96: 101.63 | E96: 58.76 | G96: 176.7935 | I96: 88.2611 | K96: 88.86 | M96: 104.02 | O96: 107.034 | Q96: 172.6532 | S96: 86.5806 | U96: 182.4408 | W96: 268.7651
A97: 45475 | C97: 101.6 | E97: 58.62 | G97: 176.9086 | I97: 88.0212 | K97: 88.99 | M97: 104.03 | O97: 106.872 | Q97: 172.8804 | S97: 86.4724 | U97: 181.9441 | W97: 268.6908
A98: 45476 | C98: 101.91 | E98: 58.96 | G98: 178.9445 | I98: 88.5993 | K98: 89.51 | M98: 104.56 | O98: 107.724 | Q98: 174.5421 | S98: 87.2089 | U98: 182.5996 | W98: 271.263
A99: 45477 | C99: 102.33 | E99: 59 | G99: 179.5285 | I99: 88.7379 | K99: 89.79 | M99: 104.89 | O99: 107.798 | Q99: 175.599 | S99: 87.4511 | U99: 182.9008 | W99: 273.3817
A100: 45478 | C100: 102.84 | E100: 59.09 | G100: 180.6879 | I100: 89.0375 | K100: 89.95 | M100: 105.32 | O100: 108.141 | Q100: 176.2196 | S100: 87.5946 | U100: 183.007 | W100: 274.7477
A101: 45479
...

Sheet NAV_Calculator
A1: ISIN | B1: Name of Mutual Fund | C1: Installment | D1: Unit provided | E1: NAV
A2: JUN | B2: Name of Mutual Fund | C2: Installment | D2: Unit provided | E2: NAV
A3: INF769K01010 | B3: Mirae Asset Mutual Fund Large Cap Fund-Regular Growth Plan-Growth -- (SIP) | C3: 1000 | D3: 13.729 | E3: =C3/D3 -> 72.838517
A4: INF200K01T28 | B4: SBI Small Cap Fund Regular Growth -- (SIP) | C4: 1000 | D4: 10.024 | E4: =C4/D4 -> 99.760575
A5: INF200K01180 | B5: SBI BLUE CHIP FUND -- (SIP) | C5: 1000 | D5: 17.519 | E5: =C5/D5 -> 57.080884
A6: INF109K01BI0 | B6: ICICI Prudential Smallcap Fund - Growth -- (SIP) | C6: 1000 | D6: 20.316 | E6: =C6/D6 -> 49.222288
A7: INF109K01BL4 | B7: ICICI Prudential Bluechip Fund - Growth -- (SIP) | C7: 1000 | D7: 15.992 | E7: =C7/D7 -> 62.531266
A8: INF846K01164 | B8: Axis Bluechip Fund -Regular Plan - Growth -- (SIP) | C8: 1000 | D8: 24.581 | E8: =C8/D8 -> 40.681827
A9: INF846K01K01 | B9: Axis Small Cap FundRegular GrowthGrowth -- (SIP) | C9: 1000 | D9: 17.531 | E9: =C9/D9 -> 57.041812
A11: JULY | B11: Name of Mutual Fund | C11: Installment | D11: Unit provided | E11: NAV
A12: INF769K01010 | B12: Mirae Asset Mutual Fund Large Cap Fund-Regular Growth Plan-Growth -- (SIP) | C12: 1000 | D12: 13.598 | E12: =C12/D12 -> 73.540227
A13: INF200K01T28 | B13: SBI Small Cap Fund Regular Growth -- (SIP) | C13: 1000 | D13: 9.977 | E13: =C13/D13 -> 100.23053
A14: INF200K01180 | B14: SBI BLUE CHIP FUND -- (SIP) | C14: 1000 | D14: 17.337 | E14: =C14/D14 -> 57.680106
A15: INF109K01BI0 | B15: ICICI Prudential Smallcap Fund - Growth -- (SIP) | C15: 1000 | D15: 19.836 | E15: =C15/D15 -> 50.41339
A16: INF109K01BL4 | B16: ICICI Prudential Bluechip Fund - Growth -- (SIP) | C16: 1000 | D16: 16.087 | E16: =C16/D16 -> 62.161994
A17: INF846K01K01 | B17: Axis Small Cap FundRegular GrowthGrowth -- (SIP) | C17: 1000 | D17: 17.43 | E17: =C17/D17 -> 57.372347
A18: INF846K01164 | B18: Axis Bluechip Fund -Regular Plan - Growth -- (SIP) | C18: 1000 | D18: 24.672 | E18: =C18/D18 -> 40.531777
A20: AUGUST | B20: Name of Mutual Fund | C20: Installment | D20: Unit provided | E20: NAV
A21: INF769K01010 | B21: Mirae Asset Mutual Fund Large Cap Fund-Regular Growth Plan-Growth -- (SIP) | C21: 1000 | D21: 12.843 | E21: =C21/D21 -> 77.863428
A22: INF200K01T28 | B22: SBI Small Cap Fund Regular Growth -- (SIP) | C22: 1000 | D22: 9.132 | E22: =C22/D22 -> 109.50504
A23: INF200K01180 | B23: SBI BLUE CHIP FUND -- (SIP) | C23: 1000 | D23: 16.269 | E23: =C23/D23 -> 61.466593
A24: INF109K01BI0 | B24: ICICI Prudential Smallcap Fund - Growth -- (SIP) | C24: 1000 | D24: 19.058 | E24: =C24/D24 -> 52.471403
A25: INF109K01BL4 | B25: ICICI Prudential Bluechip Fund - Growth -- (SIP) | C25: 1000 | D25: 15.053 | E25: =C25/D25 -> 66.43194
A26: INF846K01164 | B26: Axis Bluechip Fund -Regular Plan - Growth -- (SIP) | C26: 1000 | D26: 22.742 | E26: =C26/D26 -> 43.971506
A27: INF846K01K01 | B27: Axis Small Cap FundRegular GrowthGrowth -- (SIP) | C27: 1000 | D27: 16.217 | E27: =C27/D27 -> 61.663686
A29: SEPTEMBER | B29: Name of Mutual Fund | C29: Installment | D29: Unit provided | E29: NAV
A30: INF769K01010 | B30: Mirae Asset Mutual Fund Large Cap Fund-Regular Growth Plan-Growth -- (SIP) | C30: 1000 | D30: 12.588 | E30: =C30/D30 -> 79.440737
A31: INF200K01T28 | B31: SBI Small Cap Fund Regular Growth -- (SIP) | C31: 1000 | D31: 8.551 | E31: =C31/D31 -> 116.94539
A32: INF200K01180 | B32: SBI BLUE CHIP FUND -- (SIP) | C32: 1000 | D32: 15.774 | E32: =C32/D32 -> 63.395461
A33: INF109K01BI0 | B33: ICICI Prudential Smallcap Fund - Growth -- (SIP) | C33: 1000 | D33: 18.194 | E33: =C33/D33 -> 54.963175
A34: INF109K01BL4 | B34: ICICI Prudential Bluechip Fund - Growth -- (SIP) | C34: 1000 | D34: 14.707 | E34: =C34/D34 -> 67.994832
A35: INF846K01164 | B35: Axis Bluechip Fund -Regular Plan - Growth -- (SIP) | C35: 1000 | D35: 22.4 | E35: =C35/D35 -> 44.642857
A36: INF846K01K01 | B36: Axis Small Cap FundRegular GrowthGrowth -- (SIP) | C36: 1000 | E36: =C36/D36 -> #DIV/0!
A38: OCTOBER | B38: Name of Mutual Fund | C38: Installment | D38: Unit provided | E38: NAV
A39: INF200K01T28 | B39: SBI Small Cap Fund Regular Growth -- (SIP) | C39: 1000 | D39: 8.684 | E39: =C39/D39 -> 115.15431
A40: INF200K01180 | B40: SBI BLUE CHIP FUND -- (SIP) | C40: 1000 | D40: 16.344 | E40: =C40/D40 -> 61.184533
A41: INF109K01BI0 | B41: ICICI Prudential Smallcap Fund - Growth -- (SIP) | C41: 1000 | D41: 18.514 | E41: =C41/D41 -> 54.013179
A42: INF109K01BL4 | B42: ICICI Prudential Bluechip Fund - Growth -- (SIP) | C42: 1000 | D42: 15.064 | E42: =C42/D42 -> 66.383431
A43: INF846K01164 | B43: Axis Bluechip Fund -Regular Plan - Growth -- (SIP) | C43: 1000 | D43: 22.998 | E43: =C43/D43 -> 43.482042
A44: INF846K01K01 | B44: Axis Small Cap FundRegular GrowthGrowth -- (SIP) | C44: 1000 | D44: 15.69 | E44: =C44/D44 -> 63.734863
A45: INF769K01010 | B45: Mirae Asset Mutual Fund Large Cap Fund-Regular Growth Plan-Growth -- (SIP) | C45: 1000 | D45: 12.881 | E45: =C45/D45 -> 77.633724
A48: NOVEMBER | B48: Name of Mutual Fund | C48: Installment | D48: Unit provided | E48: NAV
A49: INF200K01T28 | B49: SBI Small Cap Fund Regular Growth -- (SIP) | C49: 1000 | D49: 8.681 | E49: =C49/D49 -> 115.1941
A50: INF200K01180 | B50: SBI BLUE CHIP FUND -- (SIP) | C50: 1000 | D50: 15.612 | E50: 64.053292
A51: INF109K01BI0 | B51: ICICI Prudential Smallcap Fund - Growth -- (SIP) | C51: 1000 | D51: 18.304 | E51: 54.632867
A52: INF109K01BL4 | B52: ICICI Prudential Bluechip Fund - Growth -- (SIP) | C52: 1000 | D52: 14.4 | E52: 69.444444
A53: INF846K01164 | B53: Axis Bluechip Fund -Regular Plan - Growth -- (SIP) | C53: 1000 | D53: 22.496 | E53: 44.452347
A54: INF846K01K01 | B54: Axis Small Cap FundRegular GrowthGrowth -- (SIP) | C54: 1000 | D54: 15.72 | E54: 63.613232
A55: INF769K01010 | B55: Mirae Asset Mutual Fund Large Cap Fund-Regular Growth Plan-Growth -- (SIP) | C55: 1000 | D55: 12.432 | E55: 80.43758
A58: DECEMBER | B58: Name of Mutual Fund | C58: Installment | D58: Unit provided | E58: NAV
A59: INF769K01010 | B59: Mirae Asset Mutual Fund Large Cap Fund-Regular Growth Plan-Growth -- (SIP) | C59: 1000 | D59: 12.118 | E59: =C59/D59 -> 82.521868
A60: INF200K01T28 | B60: SBI Small Cap Fund Regular Growth -- (SIP) | C60: 1000 | D60: 8.545 | E60: 117.0275
A61: INF200K01180 | B61: SBI BLUE CHIP FUND -- (SIP) | C61: 1000 | D61: 15.395 | E61: 64.956155
A62: INF109K01BI0 | B62: ICICI Prudential Smallcap Fund - Growth -- (SIP) | C62: 1000 | D62: 18.231 | E62: 54.851626
A63: INF109K01BL4 | B63: ICICI Prudential Bluechip Fund - Growth -- (SIP) | C63: 1000 | D63: 14.088 | E63: 70.982396
A64: INF846K01164 | B64: Axis Bluechip Fund -Regular Plan - Growth -- (SIP) | C64: 1000 | D64: 22.466 | E64: 44.511707
A65: INF846K01K01 | B65: Axis Small Cap FundRegular GrowthGrowth -- (SIP) | C65: 1000 | D65: 15.453 | E65: 64.712354
A68: JANUARY | B68: Name of Mutual Fund | C68: Installment | D68: Unit provided | E68: NAV
A69: INF769K01010 | B69: Mirae Asset Mutual Fund Large Cap Fund-Regular Growth Plan-Growth -- (SIP) | C69: 1000 | D69: 12.446 | E69: =C69/D69 -> 80.347099
A70: INF200K01T28 | B70: SBI Small Cap Fund Regular Growth -- (SIP) | C70: 1000 | D70: 8.834 | E70: 113.199
A71: INF200K01180 | B71: SBI BLUE CHIP FUND -- (SIP) | C71: 1000 | D71: 15.664 | E71: 63.840654
A72: INF109K01BI0 | B72: ICICI Prudential Smallcap Fund - Growth -- (SIP) | C72: 1000 | D72: 18.542 | E72: 53.931615
A73: INF109K01BL4 | B73: ICICI Prudential Bluechip Fund - Growth -- (SIP) | C73: 1000 | D73: 14.297 | E73: 69.944744
A74: INF846K01164 | B74: Axis Bluechip Fund -Regular Plan - Growth -- (SIP) | C74: 1000 | D74: 23.271 | E74: 42.971939
A75: INF846K01K01 | B75: Axis Small Cap FundRegular GrowthGrowth -- (SIP) | C75: 1000 | D75: 15.77 | E75: 63.411541
A78: FEBRUARY | B78: Name of Mutual Fund | C78: Installment | D78: Unit provided | E78: NAV
A79: INF769K01010 | B79: Mirae Asset Mutual Fund Large Cap Fund-Regular Growth Plan-Growth -- (SIP) | C79: 1000 | D79: 12.61 | E79: =C79/D79 -> 79.302141
A80: INF200K01T28 | B80: SBI Small Cap Fund Regular Growth -- (SIP) | C80: 1000 | D80: 8.964 | E80: 111.55734
A81: INF200K01180 | B81: SBI BLUE CHIP FUND -- (SIP) | C81: 1000 | D81: 15.739 | E81: 63.536438
A82: INF109K01BI0 | B82: ICICI Prudential Smallcap Fund - Growth -- (SIP) | C82: 1000 | D82: 18.754 | E82: 53.321958
A83: INF109K01BL4 | B83: ICICI Prudential Bluechip Fund - Growth -- (SIP) | C83: 1000 | D83: 14.471 | E83: 69.103725
A84: INF846K01164 | B84: Axis Bluechip Fund -Regular Plan - Growth -- (SIP) | C84: 1000 | D84: 23.255 | E84: 43.001505
A85: INF846K01K01 | B85: Axis Small Cap FundRegular GrowthGrowth -- (SIP) | C85: 1000 | D85: 15.651 | E85: 63.893681
A88: MARCH | B88: Name of Mutual Fund | C88: Installment | D88: Unit provided | E88: NAV
A89: INF769K01010 | B89: Mirae Asset Mutual Fund Large Cap Fund-Regular Growth Plan-Growth -- (SIP) | C89: 1000 | D89: 12.737 | E89: =C89/D89 -> 78.511423
A90: INF200K01T28 | B90: SBI Small Cap Fund Regular Growth -- (SIP) | C90: 1000 | D90: 8.985 | E90: 111.29661
A91: INF200K01180 | B91: SBI BLUE CHIP FUND -- (SIP) | C91: 1000 | D91: 15.994 | E91: 62.523446
A92: INF109K01BI0 | B92: ICICI Prudential Smallcap Fund - Growth -- (SIP) | C92: 1000 | D92: 18.747 | E92: 53.341868
A93: INF109K01BL4 | B93: ICICI Prudential Bluechip Fund - Growth -- (SIP) | C93: 1000 | D93: 14.688 | E93: 68.082789
A94: INF846K01164 | B94: Axis Bluechip Fund -Regular Plan - Growth -- (SIP) | C94: 1000 | D94: 23.922 | E94: 41.802525
A95: INF846K01K01 | B95: Axis Small Cap FundRegular GrowthGrowth -- (SIP) | C95: 1000 | D95: 15.905 | E95: 62.87331
A98: APRIL | B98: Name of Mutual Fund | C98: Installment | D98: Unit provided | E98: NAV
A99: INF200K01T28 | B99: SBI Small Cap Fund Regular Growth -- (SIP) | C99: 1000 | D99: 9.111 | E99: =C99/D99 -> 109.75744
A100: INF200K01180 | B100: SBI BLUE CHIP FUND -- (SIP) | C100: 1000 | D100: 15.938 | E100: 62.74313
A101: INF109K01BI0 | B101: ICICI Prudential Smallcap Fund - Growth -- (SIP) | C101: 1000 | D101: 18.67 | E101: 53.561864
A102: INF109K01BL4 | B102: ICICI Prudential Bluechip Fund - Growth -- (SIP) | C102: 1000 | D102: 14.591 | E102: 68.535399
A103: INF846K01K01 | B103: Axis Small Cap FundRegular GrowthGrowth -- (SIP) | C103: 1000 | D103: 15.984 | E103: 62.562563
A104: INF846K01164 | B104: Axis Bluechip Fund -Regular Plan - Growth -- (SIP) | C104: 1000 | D104: 23.757 | E104: 42.092857
A105: INF769K01010 | B105: Mirae Asset Mutual Fund Large Cap Fund-Regular Growth Plan-Growth -- (SIP) | C105: 1000 | D105: 12.865 | E105: 77.730276
A108: MAY | B108: Name of Mutual Fund | C108: Installment | D108: Unit provided | E108: NAV
A109: INF769K01010 | B109: Mirae Asset Mutual Fund Large Cap Fund-Regular Growth Plan-Growth -- (SIP) | C109: 1000 | D109: 12.464 | E109: =C109/D109 -> 80.231065
A110: INF846K01K01 | B110: Axis Small Cap FundRegular GrowthGrowth -- (SIP) | C110: 1000 | D110: 14.911 | E110: 67.064583
A111: INF846K01164 | B111: Axis Bluechip Fund -Regular Plan - Growth -- (SIP) | C111: 1000 | D111: 22.924 | E111: 43.622404
A112: INF200K01T28 | B112: SBI Small Cap Fund Regular Growth -- (SIP) | C112: 1000 | D112: 8.554 | E112: 116.90437
A113: INF200K01180 | B113: SBI BLUE CHIP FUND -- (SIP) | C113: 1000 | D113: 15.129 | E113: 66.098222
A114: INF109K01BI0 | B114: ICICI Prudential Smallcap Fund - Growth -- (SIP) | C114: 1000 | D114: 17.568 | E114: 56.921676
A115: INF109K01BL4 | B115: ICICI Prudential Bluechip Fund - Growth -- (SIP) | C115: 1000 | D115: 14.156 | E115: 70.641424
A118: JUNE | B118: Name of Mutual Fund | C118: Installment | D118: Unit provided | E118: NAV
A119: INF769K01010 | B119: Mirae Asset Mutual Fund Large Cap Fund-Regular Growth Plan-Growth -- (SIP) | C119: 1000 | D119: 12.144 | E119: =C119/D119 -> 82.345191
A120: INF200K01T28 | B120: SBI Small Cap Fund Regular Growth -- (SIP) | C120: 1000 | D120: 8.18 | E120: 122.24939
...

Sheet Profit&loss
C1: Company Name | E1: Balance | F1: Market Rate | G1: Calculated | H1: Market Value | I1: Investment | J1: V
A2: 1 | B2: INF769K01010 | C2: Mirae Asset Mutual Fund Large Cap Fund-Regular Growth Plan-Growth -- (SIP) | E2: 117.93 | F2: 79.95 | H2: 9428.5 | I2: 9000 | J2: 4.7611556
A3: 2 | B3: INF200K01T28 | C3: SBI Small Cap Fund Regular Growth -- (SIP) | E3: 98.383 | F3: 110.66 | H3: 10887.06 | I3: 9000 | J3: 20.967367
A4: 3 | B4: INF200K01180 | C4: SBI BLUE CHIP FUND -- (SIP) | E4: 274.16 | F4: 62.99 | H4: 17269.34 | I4: 15000 | J4: 15.12892
A5: 4 | B5: INF109K01BI0 | C5: ICICI Prudential Smallcap Fund - Growth -- (SIP) | E5: 201.45 | F5: 52.68 | H5: 10612.39 | I5: 9000 | J5: 17.9154
A6: 5 | B6: INF109K01BL4 | C6: ICICI Prudential Bluechip Fund - Growth -- (SIP) | E6: 157.6 | F6: 68.13 | H6: 10737.29 | I6: 9000 | J6: 19.3032
A7: 6 | B7: INF846K01K01 | C7: Axis Small Cap FundRegular GrowthGrowth -- (SIP) | E7: 279.589 | F7: 62.36 | H7: 17435.17 | I7: 15000 | J7: 16.234467
A8: 7 | B8: INF846K01164 | C8: Axis Bluechip Fund -Regular Plan - Growth -- (SIP) | E8: 232.1 | F8: 45.03 | H8: 10451.46 | I8: 9000 | J8: 16.127367
H9: 86821.21 | I9: 75000 | J9: 15.761616
A12: 1 | B12: INF769K01010 | C12: Mirae Asset Mutual Fund Large Cap Fund-Regular Growth Plan-Growth -- (SIP) | E12: 130.518 | F12: 80.1 | H12: 10454.49 | I12: 10000 | J12: 4.54492
A13: 2 | B13: INF200K01T28 | C13: SBI Small Cap Fund Regular Growth -- (SIP) | E13: 106.934 | F13: 117.53 | H13: 12567.95 | I13: 10000 | J13: 25.67953
A14: 3 | B14: INF200K01180 | C14: SBI BLUE CHIP FUND -- (SIP) | E14: 289.934 | F14: 63.61 | H14: 18442.7 | I14: 16000 | J14: 15.266887
A15: 4 | B15: INF109K01BI0 | C15: ICICI Prudential Smallcap Fund - Growth -- (SIP) | E15: 219.644 | F15: 55.38 | H15: 12163.89 | I15: 10000 | J15: 21.63885
A16: 5 | B16: INF109K01BL4 | C16: ICICI Prudential Bluechip Fund - Growth -- (SIP) | E16: 172.307 | F16: 68.12 | H16: 11737.55 | I16: 10000 | J16: 17.37553
A17: 6 | B17: INF846K01K01 | C17: Axis Small Cap FundRegular GrowthGrowth -- (SIP) | E17: 279.589 | F17: 65.17 | H17: 18220.82 | I17: 15000 | J17: 21.4721
A18: 7 | B18: INF846K01164 | C18: Axis Bluechip Fund -Regular Plan - Growth -- (SIP) | E18: 254.5 | F18: 44.91 | H18: 11429.6 | I18: 10000 | J18: 14.29595
H19: 95017 | I19: 81000 | J19: 17.304932
A22: 1 | B22: INF769K01010 | C22: Mirae Asset Mutual Fund Large Cap Fund-Regular Growth Plan-Growth -- (SIP) | E22: 143.399 | F22: 78.34 | H22: 11233.88 | I22: 11000 | J22: 2.1261605
A23: 2 | B23: INF200K01T28 | C23: SBI Small Cap Fund Regular Growth -- (SIP) | E23: 115.618 | F23: 115.46 | H23: 13349.25 | I23: 11000 | J23: 21.356857
A24: 3 | B24: INF200K01180 | C24: SBI BLUE CHIP FUND -- (SIP) | E24: 306.278 | F24: 61.95 | H24: 18973.92 | I24: 17000 | J24: 11.611306
A25: 4 | B25: INF109K01BI0 | C25: ICICI Prudential Smallcap Fund - Growth -- (SIP) | E25: 238.158 | F25: 53.65 | H25: 12777.18 | I25: 11000 | J25: 16.156152
A26: 5 | B26: INF109K01BL4 | C26: ICICI Prudential Bluechip Fund - Growth -- (SIP) | E26: 187.371 | F26: 67.11 | H26: 12574.47 | I26: 11000 | J26: 14.313344
A27: 6 | B27: INF846K01K01 | C27: Axis Small Cap FundRegular GrowthGrowth -- (SIP) | E27: 295.279 | F27: 63.67 | H27: 18800.41 | I27: 16000 | J27: 17.502587
A28: 7 | B28: INF846K01164 | C28: Axis Bluechip Fund -Regular Plan - Growth -- (SIP) | E28: 277.498 | F28: 43.75 | H28: 12140.54 | I28: 11000 | J28: 10.368523
H29: 99849.65 | I29: 88000 | J29: 13.465511
A32: 1 | B32: INF846K01164 | C32: Axis Bluechip Fund -Regular Plan - Growth -- (SIP) | E32: 299.994 | F32: 44.14 | H32: 13241.74 | I32: 12000 | J32: 10.347793
A33: 2 | B33: INF846K01K01 | C33: Axis Small Cap FundRegular GrowthGrowth -- (SIP) | E33: 310.999 | F33: 63.33 | H33: 19695.57 | I33: 17000 | J33: 15.856275
A34: 3 | B34: INF109K01BL4 | C34: ICICI Prudential Bluechip Fund - Growth -- (SIP) | E34: 201.771 | F34: 68.98 | H34: 13918.16 | I34: 12000 | J34: 15.984697
A35: 4 | B35: INF109K01BI0 | C35: ICICI Prudential Smallcap Fund - Growth -- (SIP) | E35: 256.462 | F35: 54.23 | H35: 13907.93 | I35: 12000 | J35: 15.899452
A36: 5 | B36: INF769K01010 | C36: Mirae Asset Mutual Fund Large Cap Fund-Regular Growth Plan-Growth -- (SIP) | E36: 155.831 | F36: 79.85 | H36: 12443.11 | I36: 12000 | J36: 3.6925446
A37: 6 | B37: INF200K01180 | C37: SBI BLUE CHIP FUND -- (SIP) | E37: 321.89 | F37: 63.64 | H37: 20485.08 | I37: 18000 | J37: 13.805998
A38: 7 | B38: INF200K01T28 | C38: SBI Small Cap Fund Regular Growth -- (SIP) | E38: 124.299 | F38: 114.54 | H38: 14237.21 | I38: 12000 | J38: 18.643396
H39: 107928.79 | I39: 95000 | J39: 13.609255
A43: 1 | B43: INF846K01164 | C43: Axis Bluechip Fund -Regular Plan - Growth -- (SIP) | E43: 322.46 | F43: 44.77 | H43: 14436.53 | I43: 13000 | J43: 11.050262
A44: 2 | B44: INF846K01K01 | C44: Axis Small Cap FundRegular GrowthGrowth -- (SIP) | E44: 326.452 | F44: 64.97 | H44: 21209.59 | I44: 18000 | J44: 17.831033
A45: 3 | B45: INF109K01BL4 | C45: ICICI Prudential Bluechip Fund - Growth -- (SIP) | E45: 215.859 | F45: 71.37 | H45: 15405.86 | I45: 13000 | J45: 18.506592
A46: 4 | B46: INF109K01BI0 | C46: ICICI Prudential Smallcap Fund - Growth -- (SIP) | E46: 274.693 | F46: 55.2 | H46: 15163.05 | I46: 13000 | J46: 16.638877
A47: 5 | B47: INF769K01010 | C47: Mirae Asset Mutual Fund Large Cap Fund-Regular Growth Plan-Growth -- (SIP) | E47: 167.949 | F47: 82.35 | H47: 13830.6 | I47: 13000 | J47: 6.3892308
A48: 6 | B48: INF200K01180 | C48: SBI BLUE CHIP FUND -- (SIP) | E48: 337.285 | F48: 65.28 | H48: 22017.97 | I48: 19000 | J48: 15.884026
A49: 7 | B49: INF200K01T28 | C49: SBI Small Cap Fund Regular Growth -- (SIP) | E49: 132.844 | F49: 117.44 | H49: 15601.2 | I49: 13000 | J49: 20.009223
H50: 117664.8 | I50: 102000 | J50: 15.357642
A54: 1 | B54: INF846K01164 | C54: Axis Bluechip Fund -Regular Plan - Growth -- (SIP) | E54: 345.731 | F54: 42.73 | H54: 14773.09 | I54: 14000 | J54: 5.5220429
A55: 2 | B55: INF846K01K01 | C55: Axis Small Cap FundRegular GrowthGrowth -- (SIP) | E55: 342.222 | F55: 63.19 | H55: 21625.01 | I55: 19000 | J55: 13.815832
A56: 3 | B56: INF109K01BL4 | C56: ICICI Prudential Bluechip Fund - Growth -- (SIP) | E56: 230.156 | F56: 69.82 | H56: 16069.49 | I56: 14000 | J56: 14.782086
A57: 4 | B57: INF109K01BI0 | C57: ICICI Prudential Smallcap Fund - Growth -- (SIP) | E57: 293.235 | F57: 53.85 | H57: 15790.71 | I57: 14000 | J57: 12.79075
A58: 5 | B58: INF769K01010 | C58: Mirae Asset Mutual Fund Large Cap Fund-Regular Growth Plan-Growth -- (SIP) | E58: 180.395 | F58: 80.14 | H58: 14456.86 | I58: 14000 | J58: 3.26325
A59: 6 | B59: INF200K01180 | C59: SBI BLUE CHIP FUND -- (SIP) | E59: 352.949 | F59: 63.82 | H59: 22525.21 | I59: 20000 | J59: 12.626025
A60: 7 | B60: INF200K01T28 | C60: SBI Small Cap Fund Regular Growth -- (SIP) | E60: 141.678 | F60: 111.07 | H60: 15736.18 | I60: 14000 | J60: 12.40125
H61: 120976.53 | I61: 109000 | J61: 10.987639
A64: 1 | B64: INF846K01164 | C64: Axis Bluechip Fund -Regular Plan - Growth -- (SIP) | E64: 368.986 | F64: 43.23 | H64: 15951.27 | I64: 15000 | J64: 6.3417667
A65: 2 | B65: INF846K01K01 | C65: Axis Small Cap FundRegular GrowthGrowth -- (SIP) | E65: 357.873 | F65: 63.13 | H65: 22592.52 | I65: 20000 | J65: 12.96261
A66: 3 | B66: INF109K01BL4 | C66: ICICI Prudential Bluechip Fund - Growth -- (SIP) | E66: 244.627 | F66: 69.42 | H66: 16982.01 | I66: 15000 | J66: 13.213373
A67: 4 | B67: INF109K01BI0 | C67: ICICI Prudential Smallcap Fund - Growth -- (SIP) | E67: 311.989 | F67: 52.88 | H67: 16497.98 | I67: 15000 | J67: 9.98652
A68: 5 | B68: INF769K01010 | C68: Mirae Asset Mutual Fund Large Cap Fund-Regular Growth Plan-Growth -- (SIP) | E68: 193.005 | F68: 79.54 | H68: 15351.62 | I68: 15000 | J68: 2.34412
A69: 6 | B69: INF200K01180 | C69: SBI BLUE CHIP FUND -- (SIP) | E69: 368.688 | F69: 64 | H69: 23596.03 | I69: 21000 | J69: 12.362057
A70: 7 | B70: INF200K01T28 | C70: SBI Small Cap Fund Regular Growth -- (SIP) | E70: 150.642 | F70: 111.28 | H70: 16763.44 | I70: 15000 | J70: 11.75628
H71: 127734.86 | I71: 116000 | J71: 10.116261
A74: 1 | B74: INF846K01164 | C74: Axis Bluechip Fund -Regular Plan - Growth -- (SIP) | E74: 392.908 | F74: 40.58 | G74: 15944.21 | H74: 15944.21 | I74: 16000 | J74: -0.34870625
A75: 2 | B75: INF846K01K01 | C75: Axis Small Cap FundRegular GrowthGrowth -- (SIP) | E75: 373.778 | F75: 61.26 | G75: 22897.64 | H75: 22897.64 | I75: 21000 | J75: 9.036381
A76: 3 | B76: INF109K01BL4 | C76: ICICI Prudential Bluechip Fund - Growth -- (SIP) | E76: 259.315 | F76: 66.17 | G76: 17158.87 | H76: 17158.87 | I76: 16000 | J76: 7.2429625
A77: 4 | B77: INF109K01BI0 | C77: ICICI Prudential Smallcap Fund - Growth -- (SIP) | E77: 330.736 | F77: 52.57 | G77: 17386.79 | H77: 17386.79 | I77: 16000 | J77: 8.66745
A78: 5 | B78: INF769K01010 | C78: Mirae Asset Mutual Fund Large Cap Fund-Regular Growth Plan-Growth -- (SIP) | E78: 205.742 | F78: 75.15 | G78: 15461.51 | H78: 15461.51 | I78: 16000 | J78: -3.3655563
A79: 6 | B79: INF200K01180 | C79: SBI BLUE CHIP FUND -- (SIP) | E79: 384.682 | F79: 60.7 | G79: 23350.2 | H79: 23350.2 | I79: 22000 | J79: 6.1372591
A80: 7 | B80: INF200K01T28 | C80: SBI Small Cap Fund Regular Growth -- (SIP) | E80: 159.627 | F80: 108.87 | G80: 17378.59 | H80: 17378.59 | I80: 16000 | J80: 8.6161938
H81: 129577.81 | I81: 123000 | J81: 5.3478146
A84: 1 | B84: INF846K01164 | C84: Axis Bluechip Fund -Regular Plan - Growth -- (SIP) | E84: 416.665 | F84: 42.44 | G84: 17683.26 | H84: 17683.26 | I84: 17000 | J84: 4.0191941
A85: 2 | B85: INF846K01K01 | C85: Axis Small Cap FundRegular GrowthGrowth -- (SIP) | E85: 389.762 | F85: 63.23 | G85: 24644.65 | H85: 24644.65 | I85: 22000 | J85: 12.021141
A86: 3 | B86: INF109K01BL4 | C86: ICICI Prudential Bluechip Fund - Growth -- (SIP) | E86: 273.906 | F86: 69.07 | G86: 18918.69 | H86: 18918.69 | I86: 17000 | J86: 11.286394
A87: 4 | B87: INF109K01BI0 | C87: ICICI Prudential Smallcap Fund - Growth -- (SIP) | E87: 349.406 | F87: 53.7 | G87: 18763.1 | H87: 18763.1 | I87: 17000 | J87: 10.371188
A88: 5 | B88: INF769K01010 | C88: Mirae Asset Mutual Fund Large Cap Fund-Regular Growth Plan-Growth -- (SIP) | E88: 218.607 | F88: 78.35 | G88: 17127.86 | H88: 17127.86 | I88: 17000 | J88: 0.75210588
A89: 6 | B89: INF200K01180 | C89: SBI BLUE CHIP FUND -- (SIP) | E89: 400.62 | F89: 63.56 | G89: 25463.41 | H89: 25463.41 | I89: 23000 | J89: 10.710465
A90: 7 | B90: INF200K01T28 | C90: SBI Small Cap Fund Regular Growth -- (SIP) | E90: 168.738 | F90: 110.4 | G90: 18628.68 | H90: 18628.68 | I90: 17000 | J90: 9.5804412
H91: 141229.64 | I91: 130000 | J91: 8.6381869
B94: May & June
A95: 1 | B95: INF846K01164 | C95: Axis Bluechip Fund -Regular Plan - Growth -- (SIP) | E95: 461.924 | F95: 45.14 | G95: 20851.25 | H95: 20851.25 | I95: 19000 | J95: 9.7434158
A96: 2 | B96: INF846K01K01 | C96: Axis Small Cap FundRegular GrowthGrowth -- (SIP) | E96: 418.596 | F96: 72.12 | G96: 30189.14 | H96: 30189.14 | I96: 24000 | J96: 25.7881
A97: 3 | B97: INF109K01BL4 | C97: ICICI Prudential Bluechip Fund - Growth -- (SIP) | E97: 301.715 | F97: 73.51 | G97: 22179.07 | H97: 22179.07 | I97: 19000 | J97: 16.731947
A98: 4 | B98: INF109K01BI0 | C98: ICICI Prudential Smallcap Fund - Growth -- (SIP) | E98: 383.249 | F98: 61.53 | G98: 23581.31 | H98: 23581.31 | I98: 19000 | J98: 24.112163
A99: 5 | B99: INF769K01010 | C99: Mirae Asset Mutual Fund Large Cap Fund-Regular Growth Plan-Growth -- (SIP) | E99: 243.215 | F99: 83.49 | G99: 20306.02 | H99: 20306.02 | I99: 19000 | J99: 6.8737895
A100: 6 | B100: INF200K01180 | C100: SBI BLUE CHIP FUND -- (SIP) | E100: 430.34 | F100: 68.81 | G100: 29611.7 | H100: 29611.7 | I100: 25000 | J100: 18.44678
A101: 7 | B101: INF200K01T28 | C101: SBI Small Cap Fund Regular Growth -- (SIP) | E101: 185.472 | F101: 122.79 | G101: 22774.11 | H101: 22774.11 | I101: 19000 | J101: 19.863721
H102: 169492.6 | I102: 144000 | J102: 17.703192
B105: JULY
A106: 1 | B106: INF846K01164 | C106: Axis Bluechip Fund -Regular Plan - Growth -- (SIP) | E106: 483.304 | F106: 46.55 | G106: 22497.8 | H106: 22497.8 | I106: 20000 | J106: 12.489005
A107: 2 | B107: INF846K01K01 | C107: Axis Small Cap FundRegular GrowthGrowth -- (SIP) | E107: 432.243 | F107: 73.2 | G107: 31640.19 | H107: 31640.19 | I107: 25000 | J107: 26.560752
A108: 3 | B108: INF109K01BL4 | C108: ICICI Prudential Bluechip Fund - Growth -- (SIP) | E108: 314.728 | F108: 77.33 | G108: 24337.92 | H108: 24337.92 | I108: 20000 | J108: 21.68958
A109: 4 | B109: INF109K01BI0 | C109: ICICI Prudential Smallcap Fund - Growth -- (SIP) | E109: 399.021 | F109: 63.82 | G109: 25465.52 | H109: 25465.52 | I109: 20000 | J109: 27.3276
A110: 5 | B110: INF769K01010 | C110: Mirae Asset Mutual Fund Large Cap Fund-Regular Growth Plan-Growth -- (SIP) | E110: 255.007 | F110: 86.79 | G110: 22132.06 | H110: 22132.06 | I110: 20000 | J110: 10.66029
A111: 6 | B111: INF204K01HY3 | C111: NIPPON INDIA SMALL CAP FUND - GROWTH PLAN - GROWTH -- (SIP) | E111: 8.82 | F111: 114.06 | H111: 1006.01 | I111: 1000 | J111: 0.6009
A112: 7 | B112: INF200K01180 | C112: SBI BLUE CHIP FUND -- (SIP) | E112: 444.35 | F112: 71.43 | G112: 31739.92 | H112: 31739.92 | I112: 26000 | J112: 22.076619
A113: 8 | B113: INF200K01T28 | C113: SBI Small Cap Fund Regular Growth -- (SIP) | E113: 193.319 | F113: 128 | G113: 24744.83 | H113: 24744.83 | I113: 20000 | J113: 23.72416
H114: 183564.25 | I114: 152000 | J114: 20.765951
B117: August
A118: 1 | B118: INF846K01164 | C118: Axis Bluechip Fund -Regular Plan - Growth -- (SIP) | E118: 505.252 | F118: 45.69 | G118: 23084.96 | H118: 23084.96 | I118: 21000 | J118: 9.9284
A119: 2 | B119: INF846K01K01 | C119: Axis Small Cap FundRegular GrowthGrowth -- (SIP) | E119: 445.601 | F119: 75.15 | G119: 33486.92 | H119: 33486.92 | I119: 26000 | J119: 28.795827
A120: 3 | B120: INF109K01BL4 | C120: ICICI Prudential Bluechip Fund - Growth -- (SIP) | E120: 327.704 | F120: 77.36 | G120: 25351.18 | H120: 25351.18 | I120: 21000 | J120: 20.71991
A121: 4 | B121: INF109K01BI0 | C121: ICICI Prudential Smallcap Fund - Growth -- (SIP) | E121: 414.374 | F121: 65.2 | G121: 27017.18 | H121: 27017.19 | I121: 21000 | J121: 28.653262
A122: 5 | B122: INF769K01010 | C122: Mirae Asset Mutual Fund Large Cap Fund-Regular Growth Plan-Growth -- (SIP) | E122: 266.459 | F122: 86.93 | G122: 23163.28 | H122: 23163.28 | I122: 21000 | J122: 10.301338
A123: 6 | B123: INF204K01HY3 | C123: NIPPON INDIA SMALL CAP FUND - GROWTH PLAN - GROWTH -- (SIP) | E123: 17.388 | F123: 118.44 | G123: 2059.435 | H123: 2059.44 | I123: 2000 | J123: 2.97175
A124: 7 | B124: INF200K01180 | C124: SBI BLUE CHIP FUND -- (SIP) | E124: 458.565 | F124: 70.54 | G124: 32347.18 | H124: 32347.18 | I124: 27000 | J124: 19.804352
...

Sheet Sheet1
A1: 47000 | B1: 1000 | C1: =SUM(A1:B1) -> 48000
A2: 52000 | B2: 1000 | C2: =SUM(A2:B2) -> 53000
A3: 14000 | B3: 1000 | C3: =SUM(A3:B3) -> 15000
A4: 14000 | B4: 1000 | C4: =SUM(A4:B4) -> 15000
A5: 14000 | B5: 1000 | C5: =SUM(A5:B5) -> 15000
A6: 15000 | B6: 1000 | C6: =SUM(A6:B6) -> 16000
A7: 14000 | B7: 1000 | C7: =SUM(A7:B7) -> 15000
A8: 14000 | B8: 1000 | C8: =SUM(A8:B8) -> 15000
A9: 19000 | B9: 1000 | C9: =SUM(A9:B9) -> 20000
A10: 26000 | B10: 2000 | C10: =SUM(A10:B10) -> 28000
A11: 47000 | B11: 1000 | C11: =SUM(A11:B11) -> 48000
A12: 47000 | B12: 1000 | C12: =SUM(A12:B12) -> 48000
... A20: 14000 | B20: 1000 | C20: =SUM(A20:B20) -> 15000
